poigoe/__init__.py
poigoe/__main__.py
poigoe/_main.py
poigoe/py.typed
poigoe-0.1.0.dist-info/LICENSE
poigoe-0.1.0.dist-info/WHEEL
poigoe-0.1.0.dist-info/METADATA
poigoe-0.1.0.dist-info/entry_points.txt
poigoe-0.1.0.dist-info/RECORD
