Metadata-Version: 2.1
Name: poigoe
Version: 0.1.0
Summary: Python package for realtime vocoding
Home-page: https://github.com/34j/poigoe
License: GNU General Public License v3
Author: 34j
Author-email: 34j.95a2p@simplelogin.com
Requires-Python: >=3.8,<4.0
Classifier: Development Status :: 2 - Pre-Alpha
Classifier: Intended Audience :: Developers
Classifier: License :: Other/Proprietary License
Classifier: Natural Language :: English
Classifier: Operating System :: OS Independent
Classifier: Programming Language :: Python :: 3
Classifier: Programming Language :: Python :: 3.8
Classifier: Programming Language :: Python :: 3.9
Classifier: Programming Language :: Python :: 3.10
Classifier: Programming Language :: Python :: 3.11
Classifier: Topic :: Software Development :: Libraries
Requires-Dist: click (>=8.1.3,<9.0.0)
Requires-Dist: matplotlib (>=3.7.0,<4.0.0)
Requires-Dist: numpy (>=1.24.2,<2.0.0)
Requires-Dist: praat-parselmouth (>=0.4.3,<0.5.0)
Requires-Dist: sounddevice (>=0.4.6,<0.5.0)
Requires-Dist: soundfile (>=0.12.1,<0.13.0)
Project-URL: Bug Tracker, https://github.com/34j/poigoe/issues
Project-URL: Changelog, https://github.com/34j/poigoe/blob/main/CHANGELOG.md
Project-URL: Documentation, https://poigoe.readthedocs.io
Project-URL: Repository, https://github.com/34j/poigoe
